odoo/addons/contract_price_revision/README.rst
odoo/addons/contract_price_revision/__init__.py
odoo/addons/contract_price_revision/__manifest__.py
odoo/addons/contract_price_revision/i18n/contract_price_revision.pot
odoo/addons/contract_price_revision/i18n/es.po
odoo/addons/contract_price_revision/migrations/12.0.1.0.0/pre-migration.py
odoo/addons/contract_price_revision/models/__init__.py
odoo/addons/contract_price_revision/models/contract_line.py
odoo/addons/contract_price_revision/readme/CONTRIBUTORS.rst
odoo/addons/contract_price_revision/readme/DESCRIPTION.rst
odoo/addons/contract_price_revision/readme/USAGE.rst
odoo/addons/contract_price_revision/static/description/icon.png
odoo/addons/contract_price_revision/static/description/index.html
odoo/addons/contract_price_revision/tests/__init__.py
odoo/addons/contract_price_revision/tests/test_contract_price_revision.py
odoo/addons/contract_price_revision/views/contract_line.xml
odoo/addons/contract_price_revision/wizards/__init__.py
odoo/addons/contract_price_revision/wizards/contract_price_revision.py
odoo/addons/contract_price_revision/wizards/contract_price_revision_views.xml
odoo12_addon_contract_price_revision-12.0.1.0.2.dist-info/METADATA
odoo12_addon_contract_price_revision-12.0.1.0.2.dist-info/WHEEL
odoo12_addon_contract_price_revision-12.0.1.0.2.dist-info/top_level.txt
odoo12_addon_contract_price_revision-12.0.1.0.2.dist-info/RECORD
